listener_email/__init__.py
listener_email/email.html
listener_email/email.json
listener_email/example.py
listener_email/example_email.json
listener_email-0.0.5.dist-info/LICENSE
listener_email-0.0.5.dist-info/METADATA
listener_email-0.0.5.dist-info/WHEEL
listener_email-0.0.5.dist-info/RECORD
