Metadata-Version: 2.1
Name: listener-email
Version: 0.0.5
Summary: Listener Email - Remind you of changes in your listener through email!
Home-page: https://github.com/Cierra-Runis/listener_email
License: GNU GPL v3.0
Author: Cierra_Runis
Author-email: byrdsaron@gmail.com
Requires-Python: >=3.9,<4.0
Classifier: Development Status :: 3 - Alpha
Classifier: Intended Audience :: Developers
Classifier: License :: OSI Approved :: GNU General Public License v3 or later (GPLv3+)
Classifier: License :: Other/Proprietary License
Classifier: Operating System :: OS Independent
Classifier: Programming Language :: Python :: 3
Classifier: Programming Language :: Python :: 3.9
Classifier: Programming Language :: Python :: 3.10
Classifier: Programming Language :: Python :: 3.11
Classifier: Programming Language :: Python :: 3
Classifier: Programming Language :: Python :: 3.9
Classifier: Topic :: Software Development :: Libraries :: Python Modules
Project-URL: Repository, https://github.com/Cierra-Runis/listener_email
